pywheels/__init__.py
pywheels/asker.py
pywheels/externals.py
pywheels/i18n.py
pywheels/typing.py
pywheels/algorithms/__init__.py
pywheels/algorithms/basic/__init__.py
pywheels/algorithms/basic/monotonic_queue.py
pywheels/algorithms/basic/monotonic_stack.py
pywheels/blueprints/__init__.py
pywheels/blueprints/ansatz.py
pywheels/blueprints/colean.py
pywheels/blueprints/uid_generator.py
pywheels/file_tools/__init__.py
pywheels/file_tools/basic.py
pywheels/file_tools/gif.py
pywheels/file_tools/json.py
pywheels/file_tools/mat.py
pywheels/file_tools/plot.py
pywheels/file_tools/table.py
pywheels/llm_tools/__init__.py
pywheels/llm_tools/get_answer.py
pywheels/locales/en_US/LC_MESSAGES/messages.mo
pywheels/locales/zh_CN/LC_MESSAGES/messages.mo
pywheels/math_funcs/__init__.py
pywheels/math_funcs/integral.py
pywheels/math_funcs/stat.py
pywheels/miscellaneous/__init__.py
pywheels/miscellaneous/hello.py
pywheels/miscellaneous/time_stamp.py
pywheels/numpy_tools/__init__.py
pywheels/numpy_tools/basic.py
pywheels/task_runner/__init__.py
pywheels/task_runner/task_runner.py
pywheels/type_tools/__init__.py
pywheels/type_tools/basic.py
pywheels-0.8.3.dist-info/METADATA
pywheels-0.8.3.dist-info/WHEEL
pywheels-0.8.3.dist-info/top_level.txt
pywheels-0.8.3.dist-info/RECORD
