Metadata-Version: 2.1
Name: pywheels
Version: 0.8.3
Summary: Light-weight Python wheels
Home-page: https://github.com/parkcai/pywheels
Author: parkcai
Author-email: sun_retailer@163.com
Requires-Python: >=3.8
Requires-Dist: numpy (>=1.21.0)
Requires-Dist: openai (>=1.0.0)
Requires-Dist: scipy (>=1.7.3)
Requires-Dist: openpyxl (>=3.0.10)
Requires-Dist: pandas (>=1.5.0)
Requires-Dist: astor (>=0.8.0)
Requires-Dist: aiofiles (>=23.1.0)
